cued_datalogger-0.0.19.dist-info/DESCRIPTION.rst
cued_datalogger-0.0.19.dist-info/METADATA
cued_datalogger-0.0.19.dist-info/RECORD
cued_datalogger-0.0.19.dist-info/WHEEL
cued_datalogger-0.0.19.dist-info/entry_points.txt
cued_datalogger-0.0.19.dist-info/metadata.json
cued_datalogger-0.0.19.dist-info/top_level.txt
cued_datalogger-0.0.19.dist-info/zip-safe
datalogger/VERSION
datalogger/__init__.py
datalogger/__main__.py
datalogger/acquisition_window.py
datalogger/analysis_window.py
datalogger/acquisition/ChanMetaWin.py
datalogger/acquisition/NIRecorder.py
datalogger/acquisition/RecEmitter.py
datalogger/acquisition/RecorderParent.py
datalogger/acquisition/RecordingGraph.py
datalogger/acquisition/RecordingUIs.py
datalogger/acquisition/__init__.py
datalogger/acquisition/myRecorder.py
datalogger/analysis/__init__.py
datalogger/analysis/circle_fit.py
datalogger/analysis/circle_fit_v2.py
datalogger/analysis/cwt.py
datalogger/analysis/frequency_domain.py
datalogger/analysis/sonogram.py
datalogger/analysis/test.py
datalogger/analysis/time_domain.py
datalogger/api/__init__.py
datalogger/api/addons.py
datalogger/api/channel.py
datalogger/api/file_import.py
datalogger/api/numpy_extensions.py
datalogger/api/pyqt_widgets.py
datalogger/api/pyqtgraph_extensions.py
datalogger/api/toolbox.py
datalogger/api/workspace.py
