Metadata-Version: 2.0
Name: cued-datalogger
Version: 0.0.19
Summary: The CUED DataLogger for acquiring and analysing data
Home-page: https://github.com/torebutlin/cued_datalogger
Author: Theo Brown, En Yi Tee
Author-email: tab53@cam.ac.uk, eyt21@cam.ac.uk
License: BSD 3-Clause License
Platform: UNKNOWN
